Metadata-Version: 2.1
Name: drone_troopers
Version: 0.0.2
Summary: A module for drone data processing
Author: Tech Troopers
Author-email: dhruvyadav2905@gmail.com
Classifier: Programming Language :: Python :: 3
Classifier: License :: OSI Approved :: MIT License
Classifier: Operating System :: OS Independent
Requires-Python: >=3.6
Requires-Dist: numpy
Requires-Dist: pandas
Requires-Dist: matplotlib
Requires-Dist: scikit-learn
Requires-Dist: xgboost
Requires-Dist: flask
